[
   {
      "title": "Мониторы",
      "description": false,
      "linkText": "Смотреть всё",
      "link": "404.html",
      "swiperName": "screen",
      "cards": [
         {
            "grid": true,
            "status": "orange",
            "statusName": "Хит",
            "image": "img-5.png",
            "titleCard": "27&quot; Монитор Xiaomi RMMNT27NF Black 75Hz 1920x1080 IPS",
            "price": "122 000 ₽",
            "wasprice": "",
            "condition": ""
         },
         {
            "grid": true,
            "status": "violet",
            "statusName": "Новинка",
            "image": "img-6.png",
            "titleCard": "34&quot; Монитор Huawei MateView GT ZQE-CBA Black 165Hz 3440x1440 VA",
            "price": "135 000 ₽",
            "wasprice": "",
            "condition": ""
         },
         {
            "grid": true,
            "status": "green",
            "statusName": "Скидка",
            "image": "img-7.png",
            "titleCard": "Monitor ЖК-монитор с док-станцией USB-C 279C9/01 | Philips",
            "price": "95 000 ₽",
            "wasprice": "",
            "condition": ""
         },
         {
            "grid": true,
            "status": "",
            "statusName": "",
            "image": "img-8.png",
            "titleCard": "23.8&quot; Монитор MSI Modern MD241PW белый",
            "price": "80 000 ₽",
            "wasprice": "",
            "condition": "disabled"
         }
      ]
   }
]